{"difficulty":1,"color":3,"planets":[{"planet_size":4.0,"team":2,"position_x":0.0,"position_y":0.5,"initial_population":50,"population_max":99,"is_protected":false},{"planet_size":1.0,"team":0,"position_x":0.0,"position_y":4.5,"initial_population":25,"population_max":99,"is_protected":false},{"planet_size":1.0,"team":0,"position_x":-6.5,"position_y":-3.0,"initial_population":25,"population_max":99,"is_protected":false},{"planet_size":1.0,"team":0,"position_x":6.5,"position_y":-3.0,"initial_population":25,"population_max":99,"is_protected":false}],"spaceguns":[],"turrets":[{"radius":4.0,"team":4,"position_x":-3.0,"position_y":1.5,"initial_population":99,"population_max":199,"is_protected":false},{"radius":4.0,"team":4,"position_x":-3.0,"position_y":-0.5,"initial_population":99,"population_max":150,"is_protected":false},{"radius":4.0,"team":4,"position_x":3.0,"position_y":-0.5,"initial_population":99,"population_max":150,"is_protected":false},{"radius":4.0,"team":4,"position_x":2.9000000953674318,"position_y":1.2999999523162842,"initial_population":99,"population_max":150,"is_protected":false}],"suns":[],"frozenvoids":[],"bots":[{"team":2,"type":0,"decision_interval":5.0},{"team":4,"type":2,"decision_interval":5.0}],"spaceship_speed":0.6000000238418579,"record_time":60.0,"tutorial":0}